{
    "products": [
      {
        "_id": 1,
        "name": "Raw",
        "price": 10.99,
        "description": "Pure, unfiltered and unpasteurized sweet goodness straight from the hive.",
        "image": "https://images.unsplash.com/photo-1605880980331-20a711b27338?ixlib=rb-4.0.3&ixid=M3wxMjA3fDB8MHxzZWFyY2h8NDF8fGhvbmV5fGVufDB8fDB8fHwy&auto=format&fit=crop&w=500&q=60"
      },
      {
        "_id": 11,
        "name": "BeeKissed",
        "price": 35.99,
        "description": "A unique with antibacterial qualities.",
        "image": "https://images.unsplash.com/photo-1601592149903-210683803e31?ixlib=rb-4.0.3&ixid=M3wxMjA3fDB8MHxzZWFyY2h8NjJ8fGhvbmV5fGVufDB8fDB8fHwy&auto=format&fit=crop&w=500&q=60"
      },
      
      {
        "_id": 3,
        "name": "BeeKissed",
        "price": 35.99,
        "description": "A unique with antibacterial qualities.",
        "image": "https://images.unsplash.com/photo-1601592149903-210683803e31?ixlib=rb-4.0.3&ixid=M3wxMjA3fDB8MHxzZWFyY2h8NjJ8fGhvbmV5fGVufDB8fDB8fHwy&auto=format&fit=crop&w=500&q=60"
      }
      ,
      {
        "_id": 2,
        "name": "BeeKissed",
        "price": 35.99,
        "description": "A unique with antibacterial qualities.",
        "image": "https://images.unsplash.com/photo-1601592149903-210683803e31?ixlib=rb-4.0.3&ixid=M3wxMjA3fDB8MHxzZWFyY2h8NjJ8fGhvbmV5fGVufDB8fDB8fHwy&auto=format&fit=crop&w=500&q=60"
      },{
        "_id": 4,
        "name": "Raw",
        "price": 10.99,
        "description": "Pure, unfiltered and unpasteurized sweet goodness straight from the hive.",
        "image": "https://images.unsplash.com/photo-1605880980331-20a711b27338?ixlib=rb-4.0.3&ixid=M3wxMjA3fDB8MHxzZWFyY2h8NDF8fGhvbmV5fGVufDB8fDB8fHwy&auto=format&fit=crop&w=500&q=60"
      },
      {
        "_id": 5,
        "name": "BeeKissed",
        "price": 35.99,
        "description": "A unique with antibacterial qualities.",
        "image": "https://images.unsplash.com/photo-1601592149903-210683803e31?ixlib=rb-4.0.3&ixid=M3wxMjA3fDB8MHxzZWFyY2h8NjJ8fGhvbmV5fGVufDB8fDB8fHwy&auto=format&fit=crop&w=500&q=60"
      }
      ,
      {
        "_id": 6,
        "name": "BeeKissed",
        "price": 35.99,
        "description": "A unique with antibacterial qualities.",
        "image": "https://images.unsplash.com/photo-1601592149903-210683803e31?ixlib=rb-4.0.3&ixid=M3wxMjA3fDB8MHxzZWFyY2h8NjJ8fGhvbmV5fGVufDB8fDB8fHwy&auto=format&fit=crop&w=500&q=60"
      },{
        "_id": 7,
        "name": "Raw",
        "price": 10.99,
        "description": "Pure, unfiltered and unpasteurized sweet goodness straight from the hive.",
        "image": "https://images.unsplash.com/photo-1605880980331-20a711b27338?ixlib=rb-4.0.3&ixid=M3wxMjA3fDB8MHxzZWFyY2h8NDF8fGhvbmV5fGVufDB8fDB8fHwy&auto=format&fit=crop&w=500&q=60"
      },
      {
        "_id": 8,
        "name": "Manuka",
        "price": 35.99,
        "description": "A unique with antibacterial qualities.",
        "image": "https://images.unsplash.com/photo-1601592149903-210683803e31?ixlib=rb-4.0.3&ixid=M3wxMjA3fDB8MHxzZWFyY2h8NjJ8fGhvbmV5fGVufDB8fDB8fHwy&auto=format&fit=crop&w=500&q=60"
      }
    ]
  }
  